SEDBuilder/__init__.py
SEDBuilder/spectra.py
SEDBuilder-1.0.dist-info/LICENSE
SEDBuilder-1.0.dist-info/METADATA
SEDBuilder-1.0.dist-info/WHEEL
SEDBuilder-1.0.dist-info/top_level.txt
SEDBuilder-1.0.dist-info/RECORD
