Metadata-Version: 2.1
Name: SEDBuilder
Version: 1.0
Summary: Build an SED for an object from VizieR-tabulated photometric data points
Home-page: https://github.com/zpenoyre/SEDBuilder
Author: Zephyr Penoyre
Author-email: zephyrpenoyre@gmail.com
License: MIT
Platform: UNKNOWN
